{"chunk_definitions":[{"chunk_id":"c0tr7qgxnioea","chunk_label":"unnamed-chunk-2","document_id":"51710095","expansion_state":0,"options":{"engine":"r","label":"unnamed-chunk-17"},"row":31,"row_count":1,"visible":true},{"chunk_id":"c1iz77fea5ioo","chunk_label":"unnamed-chunk-3","document_id":"51710095","expansion_state":0,"options":{"engine":"r","label":"unnamed-chunk-18"},"row":37,"row_count":1,"visible":true},{"chunk_id":"cwwi5zn6bbah6","chunk_label":"unnamed-chunk-5","document_id":"51710095","expansion_state":0,"options":{"engine":"r","label":"unnamed-chunk-53"},"row":63,"row_count":1,"visible":true},{"chunk_id":"cyawo8xiuxeo1","chunk_label":"unnamed-chunk-6","document_id":"51710095","expansion_state":0,"options":{"engine":"r","label":"unnamed-chunk-20"},"row":71,"row_count":1,"visible":true},{"chunk_id":"cqd3nj42cf86h","chunk_label":"unnamed-chunk-7","document_id":"51710095","expansion_state":0,"options":{"engine":"r","label":"unnamed-chunk-54"},"row":108,"row_count":1,"visible":true},{"chunk_id":"cl2rctau4sv1x","chunk_label":"unnamed-chunk-8","document_id":"51710095","expansion_state":0,"options":{"engine":"r","label":"unnamed-chunk-72"},"row":120,"row_count":1,"visible":true},{"chunk_id":"cn5ursugqq1ci","chunk_label":"unnamed-chunk-9","document_id":"51710095","expansion_state":0,"options":{"engine":"r","label":"unnamed-chunk-1"},"row":126,"row_count":1,"visible":true},{"chunk_id":"ctyzseda6sejc","chunk_label":"unnamed-chunk-12","document_id":"51710095","expansion_state":0,"options":{"engine":"r","label":"unnamed-chunk-3"},"row":161,"row_count":1,"visible":true},{"chunk_id":"cg5g0317n56em","chunk_label":"unnamed-chunk-13","document_id":"51710095","expansion_state":0,"options":{"engine":"r","label":"unnamed-chunk-5"},"row":167,"row_count":1,"visible":true}],"doc_write_time":1526470480}